sinflow/__init__.py
sinflow/_version.py
sinflow/flow.py
sinflow/kde.py
sinflow/mrqs.py
sinflow/tools.py
sinflow/transforms.py
sinflow-0.1.5.dist-info/LICENSE
sinflow-0.1.5.dist-info/METADATA
sinflow-0.1.5.dist-info/WHEEL
sinflow-0.1.5.dist-info/top_level.txt
sinflow-0.1.5.dist-info/RECORD
