Metadata-Version: 2.1
Name: sinflow
Version: 0.1.5
Summary: Sliced Iterative Normalizing Flow
Author-email: Minas Karamanis <minaskar@gmail.com>
Maintainer-email: Minas Karamanis <minaskar@gmail.com>
Project-URL: Homepage, https://github.com/minaskar/sinflow
Project-URL: Bug Reports, https://github.com/minaskar/sinflow/issues
Project-URL: Source, https://github.com/minaskar/sinflow
Keywords: sinf,normalizing-flow
Classifier: Development Status :: 5 - Production/Stable
Classifier: Intended Audience :: Developers
Classifier: Topic :: Software Development :: Build Tools
Classifier: License :: OSI Approved :: GNU General Public License v3 (GPLv3)
Classifier: Programming Language :: Python :: 3
Classifier: Programming Language :: Python :: 3.8
Classifier: Programming Language :: Python :: 3.9
Classifier: Programming Language :: Python :: 3.10
Classifier: Programming Language :: Python :: 3.11
Classifier: Programming Language :: Python :: 3.12
Classifier: Programming Language :: Python :: 3 :: Only
Requires-Python: >=3.8
License-File: LICENSE
Requires-Dist: numpy
Requires-Dist: scipy
Provides-Extra: dev
Requires-Dist: check-manifest; extra == "dev"
Provides-Extra: test
Requires-Dist: coverage; extra == "test"
